setup.py
Flask_fillin.egg-info/PKG-INFO
Flask_fillin.egg-info/SOURCES.txt
Flask_fillin.egg-info/dependency_links.txt
Flask_fillin.egg-info/not-zip-safe
Flask_fillin.egg-info/requires.txt
Flask_fillin.egg-info/top_level.txt
flask_fillin/__init__.py
flask_fillin/wrapper.py