Metadata-Version: 1.0
Name: Flask-fillin
Version: 0.2
Summary: A flask extension that provides utilities to test forms.
Home-page: http://github.com/jarus/flask-fillin/
Author: Christoph Heer
Author-email: christoph.heer@googlemail.com
License: BSD
Platform: any
Classifier: Environment :: Web Environment
Classifier: Intended Audience :: Developers
Classifier: License :: OSI Approved :: BSD License
Classifier: Operating System :: OS Independent
Classifier: Programming Language :: Python
Classifier: Topic :: Internet :: WWW/HTTP :: Dynamic Content
Classifier: Topic :: Software Development :: Libraries :: Python Modules
